minio_manager-0.5.1.dist-info/METADATA
minio_manager-0.5.1.dist-info/WHEEL
minio_manager-0.5.1.dist-info/entry_points.txt
minio_manager-0.5.1.dist-info/licenses/LICENSE
minio_manager/__init__.py
minio_manager/__main__.py
minio_manager/app.py
minio_manager/bucket_handler.py
minio_manager/classes/__init__.py
minio_manager/classes/controller_user.py
minio_manager/classes/errors.py
minio_manager/classes/logging_config.py
minio_manager/classes/mc_wrapper.py
minio_manager/classes/minio_resources.py
minio_manager/classes/resource_parser.py
minio_manager/classes/secrets.py
minio_manager/classes/settings.py
minio_manager/clients.py
minio_manager/policy_handler.py
minio_manager/resource_handler.py
minio_manager/resources/policies.py
minio_manager/service_account_handler.py
minio_manager/utilities.py
minio_manager-0.5.1.dist-info/RECORD
