Metadata-Version: 2.1
Name: minio-manager
Version: 0.5.1
Summary: Declare what MinIO buckets, IAM policies, ILM policies you want, and let MinIO Manager do the work.
Keywords: minio,s3,declarative
Author-Email: Alwyn Kik <alwyn@kik.pw>
License: MIT license
Project-URL: Homepage, https://alveel.github.io/minio-manager/
Project-URL: Repository, https://github.com/alveel/minio-manager
Project-URL: Documentation, https://alveel.github.io/minio-manager/
Requires-Python: >=3.11
Requires-Dist: minio>=7.2.0
Requires-Dist: pykeepass>=4.0.6
Requires-Dist: pyyaml>=6.0.1
Requires-Dist: deepdiff[optimize]>=6.7.1
Requires-Dist: pydantic-settings>=2.2.1
Requires-Dist: pydantic>=2.6.4
